fastqe/__init__.py
fastqe/fastqe.py
fastqe/fastqe_map.py
fastqe/templates/index.html
fastqe-0.5.2.dist-info/licenses/LICENSE.txt
fastqe-0.5.2.dist-info/METADATA
fastqe-0.5.2.dist-info/WHEEL
fastqe-0.5.2.dist-info/entry_points.txt
fastqe-0.5.2.dist-info/top_level.txt
fastqe-0.5.2.dist-info/RECORD
