Metadata-Version: 2.4
Name: fastqe
Version: 0.5.2
Summary: A emoji based bioinformatics command line tool
Home-page: https://github.com/fastqe/fastqe
Download-URL: https://github.com/fastqe/fastqe/tarball/v0.5.2
Author: Andrew Lonsdale
Author-email: andrew.lonsdale@lonsbio.com.au
License: BSD-3-Clause
Keywords: emoji,bioinformatics,next-generation sequencing
Classifier: Development Status :: 4 - Beta
Classifier: Environment :: Console
Classifier: Intended Audience :: Science/Research
Classifier: License :: OSI Approved :: BSD License
Classifier: Natural Language :: English
Classifier: Operating System :: MacOS :: MacOS X
Classifier: Operating System :: POSIX
Classifier: Operating System :: Unix
Classifier: Programming Language :: Python
Classifier: Topic :: Scientific/Engineering
Classifier: Topic :: Scientific/Engineering :: Bio-Informatics
License-File: LICENSE.txt
Requires-Dist: jinja2
Requires-Dist: biopython>=1.66
Requires-Dist: pyemojify
Requires-Dist: setuptools>=38.6
Dynamic: author
Dynamic: author-email
Dynamic: classifier
Dynamic: description
Dynamic: description-content-type
Dynamic: download-url
Dynamic: home-page
Dynamic: keywords
Dynamic: license
Dynamic: license-file
Dynamic: requires-dist
Dynamic: summary
